django_odm2/__init__.py
django_odm2/admin.py
django_odm2/apps.py
django_odm2/querysets.py
django_odm2/tests.py
django_odm2/views.py
django_odm2/migrations/0001_initial.py
django_odm2/migrations/__init__.py
django_odm2/models/__init__.py
django_odm2/models/abstracts.py
django_odm2/models/analyses.py
django_odm2/models/annotations.py
django_odm2/models/core.py
django_odm2/models/equipment.py
django_odm2/models/features.py
django_odm2/models/identifiers.py
django_odm2/models/properties.py
django_odm2/models/provenance.py
django_odm2/models/quality.py
django_odm2/models/results.py
django_odm2/models/simulation.py
django_odm2/models/vocabularies.py
django_odm2-0.0.2.dist-info/METADATA
django_odm2-0.0.2.dist-info/WHEEL
django_odm2-0.0.2.dist-info/top_level.txt
django_odm2-0.0.2.dist-info/RECORD
