Metadata-Version: 2.1
Name: django-odm2
Version: 0.0.2
Summary: Django-odm2 maps the ODM2 model to django ORM
Home-page: https://github.com/lyralemos/django-odm2
Author: Alexandre Marinho
Author-email: lyralemos@gmail.com
Maintainer: Alexandre Marinho
Maintainer-email: lyralemos@gmail.com
License: MIT license
Keywords: django-odm2
Platform: UNKNOWN
Classifier: Development Status :: 3 - Alpha
Classifier: Intended Audience :: Developers
Classifier: Programming Language :: Python :: 3.6
Classifier: Programming Language :: Python :: 3.7
Classifier: Programming Language :: Python :: 3.8
Requires-Dist: django (>=4.0.6)
